pelican/plugins/email_cloak/__init__.py
pelican/plugins/email_cloak/email_cloak.py
pelican_email_cloak-0.2.0.dist-info/LICENSE
pelican_email_cloak-0.2.0.dist-info/METADATA
pelican_email_cloak-0.2.0.dist-info/WHEEL
pelican_email_cloak-0.2.0.dist-info/RECORD
