Metadata-Version: 2.1
Name: pelican-email-cloak
Version: 0.2.0
Summary: E-mail cloaking plugin for Pelican
Home-page: https://github.com/deme3/pelican-email-cloak
License: MIT
Keywords: pelican,plugin
Author: Demetrio Battaglia
Author-email: deme3.iot@gmail.com
Requires-Python: >=3.8.1,<4.0
Classifier: Development Status :: 5 - Production/Stable
Classifier: Environment :: Console
Classifier: Framework :: Pelican
Classifier: Framework :: Pelican :: Plugins
Classifier: Intended Audience :: End Users/Desktop
Classifier: License :: OSI Approved :: MIT License
Classifier: Operating System :: OS Independent
Classifier: Programming Language :: Python :: 3
Classifier: Programming Language :: Python :: 3.9
Classifier: Programming Language :: Python :: 3.10
Classifier: Programming Language :: Python :: 3.11
Classifier: Topic :: Internet :: WWW/HTTP
Classifier: Topic :: Software Development :: Libraries :: Python Modules
Provides-Extra: markdown
Requires-Dist: mailscrambler (>=0.1.2)
Requires-Dist: markdown (>=3.2) ; extra == "markdown"
Requires-Dist: pelican (>=4.5)
Project-URL: Documentation, https://docs.getpelican.com
Project-URL: Funding, https://donate.getpelican.com/
Project-URL: Issue Tracker, https://github.com/deme3/pelican-email-cloak/issues
Project-URL: Repository, https://github.com/deme3/pelican-email-cloak
